fastapi_blocks/__init__.py
fastapi_blocks/__main__.py
fastapi_blocks/block_manager.py
fastapi_blocks/cli.py
fastapi_blocks/py.typed
fastapi_blocks/settings.py
fastapi_blocks/utils.py
fastapi_blocks/default_blocks/block_template/__init__.py
fastapi_blocks/default_blocks/block_template/api_router.py
fastapi_blocks/default_blocks/block_template/router.py
fastapi_blocks/default_blocks/block_template/settings.py
fastapi_blocks/default_blocks/homepage_block/__init__.py
fastapi_blocks/default_blocks/homepage_block/api_router.py
fastapi_blocks/default_blocks/homepage_block/router.py
fastapi_blocks/default_blocks/homepage_block/settings.py
fastapi_blocks-0.1.5.dist-info/licenses/LICENSE
fastapi_blocks-0.1.5.dist-info/METADATA
fastapi_blocks-0.1.5.dist-info/WHEEL
fastapi_blocks-0.1.5.dist-info/entry_points.txt
fastapi_blocks-0.1.5.dist-info/top_level.txt
fastapi_blocks-0.1.5.dist-info/RECORD
