Metadata-Version: 2.4
Name: fastapi-blocks
Version: 0.1.5
Summary: A library for creating modular FastAPI applications.
Author: r3sbarra)
License: MIT
Classifier: Programming Language :: Python :: 3
Classifier: Operating System :: OS Independent
Classifier: Framework :: FastAPI
Requires-Python: >=3.11
License-File: LICENSE
Requires-Dist: fastapi
Requires-Dist: pydantic
Requires-Dist: pydantic-settings
Requires-Dist: tomli-w
Requires-Dist: jinja2
Requires-Dist: dirhash
Provides-Extra: dev
Requires-Dist: pytest; extra == "dev"
Requires-Dist: httpx; extra == "dev"
Dynamic: license-file
